stratopy/IO.py
stratopy/__init__.py
stratopy/cloudsat.py
stratopy/core.py
stratopy/goes.py
StratoPy-0.1.1.dist-info/LICENSE
StratoPy-0.1.1.dist-info/METADATA
StratoPy-0.1.1.dist-info/WHEEL
StratoPy-0.1.1.dist-info/top_level.txt
StratoPy-0.1.1.dist-info/RECORD
