Metadata-Version: 2.1
Name: StratoPy
Version: 0.1.1
Summary: Python library designed to easily manipulate CloudSat and GOES-R data and generate labeled images containing cloud types.
Home-page: https://github.com/paula-rj/StratoPy
Author: Paula Romero, Georgynio Rosales, Jose Robledo, Julian Villa
Author-email: paula.romero@mi.unc.edu.ar
License: The MIT License
Keywords: stratopy,clouds
Classifier: Development Status :: 4 - Beta
Classifier: Intended Audience :: Education
Classifier: Intended Audience :: Science/Research
Classifier: Programming Language :: Python :: 3.9
License-File: LICENSE
Requires-Dist: numpy
Requires-Dist: pandas
Requires-Dist: attrs
Requires-Dist: matplotlib
Requires-Dist: geopandas
Requires-Dist: pyhdf
Requires-Dist: pyorbital
Requires-Dist: pyspectral
Requires-Dist: netCDF4
Requires-Dist: diskcache
Requires-Dist: s3fs
